{
    "interactionModel": {
        "languageModel": {
            "intents": [
                {
                    "name": "flexaIntent",
                    "samples": [
                        "trade school",
                        "trade",
                        "go to trade school"
                    ]
                },
                {
                    "name": "flexbIntent",
                    "samples": [
                        "public college",
                        "go to public college",
                        "public"
                    ]
                },
                {
                    "name": "flexcIntent",
                    "samples": [
                        "private college",
                        "private",
                        "go to private college"
                    ]
                },
                {
                    "name": "flexdIntent",
                    "samples": [
                        "party college",
                        "party school",
                        "party",
                        "go to party school",
                        "go out and party",
                        "party life"
                    ]
                },
                {
                    "name": "flexeIntent",
                    "samples": [
                        "science",
                        "study science"
                    ]
                },
                {
                    "name": "flexfIntent",
                    "samples": [
                        "art",
                        "study art"
                    ]
                },
                {
                    "name": "flexgIntent",
                    "samples": [
                        "study",
                        "focus on studies",
                        "focus on my studies",
                        "studies",
                        "study life"
                    ]
                },
                {
                    "name": "flexhIntent",
                    "samples": [
                        "both",
                        "try to do both",
                        "do both"
                    ]
                },
                {
                    "name": "flexiIntent",
                    "samples": [
                        "parent's house",
                        "live at home",
                        "live with parents",
                        "parents"
                    ]
                },
                {
                    "name": "flexjIntent",
                    "samples": [
                        "rent apartment",
                        "get apartment",
                        "apartment",
                        "rent"
                    ]
                },
                {
                    "name": "flexkIntent",
                    "samples": [
                        "programmer"
                    ]
                },
                {
                    "name": "flexlIntent",
                    "samples": [
                        "doctor"
                    ]
                },
                {
                    "name": "flexmIntent",
                    "samples": [
                        "forensic scientist"
                    ]
                },
                {
                    "name": "flexnIntent",
                    "samples": [
                        "teacher"
                    ]
                },
                {
                    "name": "flexoIntent",
                    "samples": [
                        "writer"
                    ]
                },
                {
                    "name": "flexpIntent",
                    "samples": [
                        "designer"
                    ]
                },
                {
                    "name": "flexqIntent",
                    "samples": [
                        "contractor"
                    ]
                },
                {
                    "name": "flexrIntent",
                    "samples": [
                        "auto mechanic"
                    ]
                },
                {
                    "name": "flexsIntent",
                    "samples": [
                        "electrician"
                    ]
                },
                {
                    "name": "flextIntent",
                    "samples": [
                        "country",
                        "live out in the country",
                        "in the country",
                        "the country"
                    ]
                },
                {
                    "name": "flexuIntent",
                    "samples": [
                        "city",
                        "big city",
                        "live in the city",
                        "in the city",
                        "the city"
                    ]
                },
                {
                    "name": "flexvIntent",
                    "samples": [
                        "suburb",
                        "suburbs",
                        "in the suburbs",
                        "the suburbs"
                    ]
                },
                {
                    "name": "flexwIntent",
                    "samples": [
                        "fund",
                        "set up fund"
                    ]
                },
                {
                    "name": "flexxIntent",
                    "samples": [
                        "don't set up fund"
                    ]
                },
                {
                    "name": "flexyIntent",
                    "samples": [
                        "married",
                        "get married",
                        "marry"
                    ]
                },
                {
                    "name": "flexzIntent",
                    "samples": [
                        "single",
                        "stay single",
                        "be alone"
                    ]
                },
                {
                    "name": "flexbaIntent",
                    "samples": [
                        "big",
                        "big wedding",
                        "big one"
                    ]
                },
                {
                    "name": "flexbbIntent",
                    "samples": [
                        "small",
                        "small one",
                        "small wedding"
                    ]
                },
                {
                    "name": "flexbcIntent",
                    "samples": [
                        "have kids",
                        "want kids",
                        "try to have kids"
                    ]
                },
                {
                    "name": "flexbdIntent",
                    "samples": [
                        "don't have kids",
                        "no kids",
                        "don't want kids"
                    ]
                },
                {
                    "name": "flexbeIntent",
                    "samples": [
                        "retire",
                        "retire from work"
                    ]
                },
                {
                    "name": "flexbfIntent",
                    "samples": [
                        "keep working"
                    ]
                },
                {
                    "name": "AMAZON.CancelIntent"
                },
                {
                    "name": "AMAZON.HelpIntent"
                },
                {
                    "name": "AMAZON.LoopOffIntent"
                },
                {
                    "name": "AMAZON.LoopOnIntent"
                },
                {
                    "name": "AMAZON.NextIntent"
                },
                {
                    "name": "AMAZON.NoIntent"
                },
                {
                    "name": "AMAZON.PauseIntent"
                },
                {
                    "name": "AMAZON.PreviousIntent"
                },
                {
                    "name": "AMAZON.RepeatIntent"
                },
                {
                    "name": "AMAZON.ResumeIntent"
                },
                {
                    "name": "AMAZON.ShuffleOffIntent"
                },
                {
                    "name": "AMAZON.ShuffleOnIntent"
                },
                {
                    "name": "AMAZON.StartOverIntent"
                },
                {
                    "name": "AMAZON.StopIntent"
                },
                {
                    "name": "AMAZON.YesIntent"
                },
                {
                    "name": "AMAZON.ScrollUpIntent"
                },
                {
                    "name": "AMAZON.ScrollLeftIntent"
                },
                {
                    "name": "AMAZON.ScrollDownIntent"
                },
                {
                    "name": "AMAZON.ScrollRightIntent"
                },
                {
                    "name": "AMAZON.PageUpIntent"
                },
                {
                    "name": "AMAZON.PageDownIntent"
                },
                {
                    "name": "AMAZON.MoreIntent"
                },
                {
                    "name": "AMAZON.FallbackIntent"
                }
            ],
            "invocationName": "life simulator"
        }
    }
}